{"$type":"List`1","$values":[{"$id":"1","$type":"ProjectOptionEntry","key":"NetworkCollapsed","context":"{2232342-1703}","value":false},{"$id":"2","$type":"ProjectOptionEntry","key":"RestoreNetworkStates","context":"{2232321-1692}","value":true},{"$id":"3","$type":"ProjectOptionEntry","key":"LastSelection@Siemens.Simatic.PlcLanguages.SCLEditor.SCLEditorView","context":"{2232321-4159}","value":{"$id":"4","$type":"SessionDataUndo","CaretPositionRC":"44, 1"}},{"$id":"5","$type":"ProjectOptionEntry","key":"NetworkCollapsed","context":"{2232342-6198}","value":false},{"$id":"6","$type":"ProjectOptionEntry","key":"RestoreNetworkStates","context":"{2232321-6195}","value":true},{"$id":"7","$type":"ProjectOptionEntry","key":"NetworkCollapsed","context":"{2232342-6208}","value":false},{"$id":"8","$type":"ProjectOptionEntry","key":"NetworkCollapsed","context":"{2232342-6203}","value":false},{"$id":"9","$type":"ProjectOptionEntry","key":"NetworkCollapsed","context":"{2232342-6204}","value":false},{"$id":"10","$type":"ProjectOptionEntry","key":"NetworkCollapsed","context":"{2232342-6260}","value":false},{"$id":"11","$type":"ProjectOptionEntry","key":"NetworkCollapsed","context":"{2232342-6273}","value":false}]}